{
    "id":  5345,
    "date":  "2022-12-29T08:27:17",
    "date_gmt":  "2022-12-29T01:27:17",
    "guid":  {
                 "rendered":  "https://kyujin.careerlink.asia/blog/?p=5345"
             },
    "modified":  "2026-01-17T20:19:47",
    "modified_gmt":  "2026-01-17T13:19:47",
    "slug":  "%e3%83%9b%e3%82%a4%e3%82%a2%e3%83%b3%e3%81%8a%e3%81%99%e3%81%99%e3%82%81%e3%81%ae%e9%ab%98%e7%b4%9a5%e3%81%a4%e6%98%9f%e3%83%9b%e3%83%86%e3%83%ab",
    "status":  "publish",
    "type":  "post",
    "link":  "https://kyujin.careerlink.asia/blog/%e3%83%9b%e3%82%a4%e3%82%a2%e3%83%b3%e3%81%8a%e3%81%99%e3%81%99%e3%82%81%e3%81%ae%e9%ab%98%e7%b4%9a5%e3%81%a4%e6%98%9f%e3%83%9b%e3%83%86%e3%83%ab/",
    "title":  {
                  "rendered":  "ホイアンでおすすめの高級5つ星ホテル6選"
              },
    "content":  {
                    "rendered":  "\u003cp\u003e\u003cem\u003e　\u003c/em\u003eホイアンはベトナムの中部、トゥボン川の河口に位置しています。ベトナムの古都ホイアンは1999年に「ホイアンの古い町並み」として世界遺産に登録されました。リゾート地のダナンからも近いところにあり、また違ったベトナムの一面を見ることができます。少し足を伸ばしてホイアンを訪れてみませんか？ベトナムといえばフォーやバインミーを思い浮かべる方もいるでしょう。ホイアンでは美味しいフォー、バインミーが食べられるお店やおしゃれなカフェ、レストランも建ち並んでいるためベトナムのローカルフードを楽しみたい方におすすめです。ここでは、ホイアンでの滞在をより快適にしてくれる5つ星の高級ホテルの中で、ホイアンに滞在したことのある筆者がおすすめする6つのホテルを紹介します。\u003c/p\u003e\n\u003cdiv class=\"box_style box_style_blue\"\u003e\n\u003cdiv class=\"box_inner\"\u003e\n\u003cdiv class=\"box_style_title\"\u003e\u003cspan\u003eこの記事はこんな方におすすめ\u003c/span\u003e\u003c/div\u003e\n\u003cp\u003e・世界遺産で宿泊をしてみたい方\u003cbr /\u003e\n・穏やかな旅を楽しみたい方\u003cbr /\u003e\n・ベトナムのローカルフードを楽しみたい方\u003c/p\u003e\n\u003c/div\u003e\n\u003c/div\u003e\n\u003cp\u003eこちらで紹介するホテルのいくつかは、市内中心部から離れています。気になった方はぜひ一度ホテルの場所を地図で確認してからご予約ください。それでは一つずつ紹介していきます。\u003c/p\u003e\n\u003ch4\u003e\u003cspan class=\"line-yellow\"\u003e\u003cstrong\u003eアナンタラ ホイ アン リゾート（Anantara Hoi An Resort）\u003c/strong\u003e\u003c/span\u003e\u003c/h4\u003e\n\u003cp\u003e\u003ca href=\"https://www.agoda.com/partners/partnersearch.aspx?pcs=10\u0026amp;cid=1888557\u0026amp;hl=ja\u0026amp;hid=48367\" target=\"_blank\" rel=\"noopener\"\u003e\u003cimg decoding=\"async\" src=\"//pix8.agoda.net/hotelImages/23112667/0/4165a05fd3aa5eb2c67bc10b4d794cf8.jpg?ca=17\u0026amp;ce=1\u0026amp;s=480x360\" srcset=\"//pix8.agoda.net/hotelImages/23112667/0/4165a05fd3aa5eb2c67bc10b4d794cf8.jpg?ca=17\u0026amp;ce=1\u0026amp;s=480x360 1x, //pix8.agoda.net/hotelImages/23112667/0/4165a05fd3aa5eb2c67bc10b4d794cf8.jpg?ca=17\u0026amp;ce=1\u0026amp;s=960x720 2x\" /\u003e\u003c/a\u003e\u003c/p\u003e\n\u003cp\u003e\u003cem\u003e　\u003c/em\u003e最後に紹介するのはこちら、アナンタラ ホイアン リゾートです。こちらのホテルは市内中心部のトゥボン川沿いに位置しています。リバーフロントのテラスでのダイニングは必須です。ホイアンの雰囲気を味わいながらベトナム料理を楽しめます。夜になると鮮やかなランタンと人々の賑わいがまた昼とは違う雰囲気を醸し出していて面白いです。お部屋にはリバービューとガーデンビューの2種類があります。ホイアンの雰囲気を味わいたい方はリバービュー、ゆったりとした雰囲気のなかで過ごしたい方にはガーデンビューがおすすめです。キッズクラブもあるので、ファミリーステイの方にもおすすめ。お子さんも退屈せずに滞在することができます。旧市街からも近いためどこに観光へ行くにも便利で、疲れたらすぐにホテルに戻って来られます。ホイアンを存分に楽しんでください。\u003c/p\u003e\n\u003cdiv class=\"al-c m20\"\u003e\u003ca href=\"https://www.agoda.com/partners/partnersearch.aspx?pcs=1\u0026amp;cid=1888557\u0026amp;hl=ja-jp\u0026amp;hid=48367\" class=\"btn dir-arw_r btn_bluegreen\" target=\"_blank\" rel=\"noopener noreferrer\"\u003e\u003cspan class=\"icon_arrow_s_right\"\u003e\u003c/span\u003eアゴダで「アナンタラ ホイ アン リゾート」を予約する\u003c/a\u003e\u003c/div\u003e\n\u003cdiv class=\"box_style box_style02\"\u003e\n\u003cdiv class=\"box_inner\"\u003e\u003cspan class=\"orange b\"\u003eアナンタラ ホイ アン リゾート（Anantara Hoi An Resort）\u003c/span\u003e\u003cbr /\u003e\n住所：1 Pham Hong Thai, カムチャウ, ホイアン, ベトナム\u003cbr /\u003e\nURL：\u003ca href=\"https://www.anantara.com/hoi-an?utm_source=GoogleMyBusiness\u0026amp;utm_medium=GMB\u0026amp;utm_term=HoiAn\u0026amp;utm_content=Home\u0026amp;utm_campaign=Google_GMB\" target=\"_blank\" rel=\"noopener noreferrer\"\u003ehttps://www.anantara.com/\u003c/a\u003e\u003c/div\u003e\n\u003cdiv class=\"box_inner\"\u003e\n\u003cp\u003e\u003ciframe width=\"600\" height=\"450\" style=\"border: 0;\" src=\"https://www.google.com/maps/embed?pb=!1m18!1m12!1m3!1d3837.607460073939!2d108.33396741487249!3d15.877215448772358!2m3!1f0!2f0!3f0!3m2!1i1024!2i768!4f13.1!3m3!1m2!1s0x31420dd44606dd4d%3A0x9ac1929fe84bc40b!2z44Ki44OK44Oz44K_44OpIOODm-OCpOOCouODsyDjg6rjgr7jg7zjg4g!5e0!3m2!1sja!2sjp!4v1672035541547!5m2!1sja!2sjp\" allowfullscreen=\"allowfullscreen\" loading=\"lazy\" referrerpolicy=\"no-referrer-when-downgrade\"\u003e\u003c/iframe\u003e\u003c/p\u003e\n\u003c/div\u003e\n\u003c/div\u003e\n\u003ch4\u003e\u003cspan class=\"line-yellow\"\u003e\u003cstrong\u003eアレグロ ホイアン ア リトル ラグジュアリー ホテル＆スパ（Allegro Hoi An. A LIttle Luxury Hotel \u0026amp; Spa）\u003c/strong\u003e\u003c/span\u003e\u003c/h4\u003e\n\u003cp\u003e\u003ca href=\"https://www.agoda.com/partners/partnersearch.aspx?pcs=10\u0026amp;cid=1888557\u0026amp;hl=ja\u0026amp;hid=4034720\" target=\"_blank\" rel=\"noopener\"\u003e\u003cimg decoding=\"async\" src=\"//pix8.agoda.net/hotelImages/4034720/-1/47269e87437d0e4500d048b73efb6f64.jpg?ca=7\u0026amp;ce=1\u0026amp;s=480x360\" srcset=\"//pix8.agoda.net/hotelImages/4034720/-1/47269e87437d0e4500d048b73efb6f64.jpg?ca=7\u0026amp;ce=1\u0026amp;s=480x360 1x, //pix8.agoda.net/hotelImages/4034720/-1/47269e87437d0e4500d048b73efb6f64.jpg?ca=7\u0026amp;ce=1\u0026amp;s=960x720 2x\" /\u003e\u003c/a\u003e\u003c/p\u003e\n\u003cp\u003e\u003cem\u003e　\u003c/em\u003eこちらのホテルは旧市街の少し北にあるチャンフンダオ通り沿いにあります。市内中心部に位置しているため、ホイアンの街を散策したい方におすすめのホテルです。部屋の内装も可愛くて、清潔感があるため女性の一人旅にもおすすめです。朝食のビュッフェではベトナムのローカルフードも食べられるのがいいですね。口コミでも朝食が高く評価されています。ホテルが無料で自転車を貸し出してくれるので、旅で歩くのに疲れた方も散策を楽しめます。ホテルステイを楽しみたい方は、ホテルに併設されているプールサイドバーで時間を忘れてゆっくりしてみるのもいいですね。夜の観光を楽しみたい方はホイアンナイトマーケットへも徒歩10分で行くことができるので、ホイアンの夜の街並みも十分楽しんでいただけます。\u003c/p\u003e\n\u003cdiv class=\"al-c m20\"\u003e\u003ca href=\"https://www.agoda.com/partners/partnersearch.aspx?pcs=1\u0026amp;cid=1888557\u0026amp;hl=ja-jp\u0026amp;hid=4034720\" class=\"btn dir-arw_r btn_bluegreen\" target=\"_blank\" rel=\"noopener noreferrer\"\u003e\u003cspan class=\"icon_arrow_s_right\"\u003e\u003c/span\u003eアゴダで「アレグロ ホイアン ア リトル ラグジュアリー ホテル＆スパ」を予約する\u003c/a\u003e\u003c/div\u003e\n\u003cdiv class=\"box_style box_style02\"\u003e\n\u003cdiv class=\"box_inner\"\u003e\n\u003cp\u003e\u003cspan class=\"orange b\"\u003eアレグロ ホイアン ア リトル ラグジュアリー ホテル＆スパ（Allegro Hoi An. A LIttle Luxury Hotel \u0026amp; Spa）\u003c/span\u003e\u003cbr /\u003e\n住所：86 Tran Hung Dao Street, Hoi An City, Quang Nam Province, カムフォー, ホイアン, ベトナム\u003cbr /\u003e\nURL：\u003ca href=\"http://allegrohoian.com/\" target=\"_blank\" rel=\"noopener noreferrer\"\u003ehttp://allegrohoian.com/\u003c/a\u003e\u003c/p\u003e\n\u003cp\u003e\u003ciframe width=\"600\" height=\"450\" style=\"border: 0;\" src=\"https://www.google.com/maps/embed?pb=!1m18!1m12!1m3!1d3837.5397600416873!2d108.32236511487243!3d15.880768748679074!2m3!1f0!2f0!3f0!3m2!1i1024!2i768!4f13.1!3m3!1m2!1s0x31420e7b8af8c4a7%3A0xf9e6c130802308fd!2sAllegro%20Hoi%20An%20.%20A%20Little%20Luxury%20Hotel%20%26%20Spa!5e0!3m2!1sja!2sjp!4v1672035618373!5m2!1sja!2sjp\" allowfullscreen=\"allowfullscreen\" loading=\"lazy\" referrerpolicy=\"no-referrer-when-downgrade\"\u003e\u003c/iframe\u003e\u003c/p\u003e\n\u003c/div\u003e\n\u003c/div\u003e\n\u003ch4\u003e\u003cspan class=\"line-yellow\"\u003e\u003cstrong\u003eリトル リバーサイド ア ラグジュアリー ホテル＆スパ（Little Riverside.A Luxury Hotel \u0026amp; Spa）\u003c/strong\u003e\u003c/span\u003e\u003c/h4\u003e\n\u003cp\u003e\u003ca href=\"https://www.agoda.com/partners/partnersearch.aspx?pcs=10\u0026amp;cid=1888557\u0026amp;hl=ja\u0026amp;hid=4997756\" target=\"_blank\" rel=\"noopener\"\u003e\u003cimg decoding=\"async\" src=\"//pix8.agoda.net/hotelImages/4997756/-1/57cade84db4dd0a2715dc95564e8fdfd.jpg?ca=11\u0026amp;ce=1\u0026amp;s=480x360\" srcset=\"//pix8.agoda.net/hotelImages/4997756/-1/57cade84db4dd0a2715dc95564e8fdfd.jpg?ca=11\u0026amp;ce=1\u0026amp;s=480x360 1x, //pix8.agoda.net/hotelImages/4997756/-1/57cade84db4dd0a2715dc95564e8fdfd.jpg?ca=11\u0026amp;ce=1\u0026amp;s=960x720 2x\" /\u003e\u003c/a\u003e\u003c/p\u003e\n\u003cp\u003e\u003cem\u003e　\u003c/em\u003eこちらのホテルは市内中心部、トゥボン川沿いにあります。2022年度のAgoda トラベラーズ ベストチョイス賞にも選ばれているホテルで、注目度が上がっています。こじんまりとした小規模ホテルなので気になった方は早めの予約をおすすめします。こちらのホテルは観光を楽しみたい方におすすめ。旧市街の東側に位置し、観光で賑わっている場所からは少し離れています。しかし気になっている観光スポットやカフェへはほぼどこへでも徒歩で行くことができます！と言えるぐらいアクセス抜群の立地です。また周辺スポットへはシャトルサービスもあるのでアクセスも簡単です。ナイトマーケットもすぐそこにあるので、夜遅くなってもすぐホテルのお部屋に戻れるのがいいですよね。リバービューのお部屋もあるので疲れたらお部屋に戻ってホイアンの街を眺めながらゆっくりできるのも魅力的です。\u003c/p\u003e\n\u003cdiv class=\"al-c m20\"\u003e\u003ca href=\"https://www.agoda.com/partners/partnersearch.aspx?pcs=1\u0026amp;cid=1888557\u0026amp;hl=ja-jp\u0026amp;hid=4997756\" class=\"btn dir-arw_r btn_bluegreen\" target=\"_blank\" rel=\"noopener noreferrer\"\u003e\u003cspan class=\"icon_arrow_s_right\"\u003e\u003c/span\u003eアゴダで「リトル リバーサイド ア ラグジュアリー ホテル＆スパ」を予約する\u003c/a\u003e\u003c/div\u003e\n\u003cdiv class=\"box_style box_style02\"\u003e\n\u003cdiv class=\"box_inner\"\u003e\u003cspan class=\"orange b\"\u003eリトル リバーサイド ア ラグジュアリー ホテル＆スパ（Little Riverside.A Luxury Hotel \u0026amp; Spa）\u003c/span\u003e\u003cbr /\u003e\n住所：09 Phan Boi Chau, カムチャウ, ホイアン, ベトナム\u003cbr /\u003e\nURL：\u003ca href=\"https://www.littleriversidehoian.com/\" target=\"_blank\" rel=\"noopener noreferrer\"\u003ehttps://www.littleriversidehoian.com/\u003c/a\u003e\u003c/div\u003e\n\u003cdiv class=\"box_inner\"\u003e\n\u003cp\u003e\u003ciframe width=\"600\" height=\"450\" style=\"border: 0;\" src=\"https://www.google.com/maps/embed?pb=!1m18!1m12!1m3!1d3837.607936339668!2d108.33491011487253!3d15.877190448772957!2m3!1f0!2f0!3f0!3m2!1i1024!2i768!4f13.1!3m3!1m2!1s0x31420dd44ca499dd%3A0xad045ebc07d978f0!2sLittle%20Riverside%20Hoi%20An%20-%20Little%20Luxury%20Hotel%20%26%20Spa!5e0!3m2!1sja!2sjp!4v1672035717337!5m2!1sja!2sjp\" allowfullscreen=\"allowfullscreen\" loading=\"lazy\" referrerpolicy=\"no-referrer-when-downgrade\"\u003e\u003c/iframe\u003e\u003c/p\u003e\n\u003c/div\u003e\n\u003c/div\u003e\n\u003ch4\u003e\u003cspan class=\"line-yellow\"\u003e\u003cstrong\u003eラ シエスタ ホイ アン リゾート＆スパ（La Siesta Hoi An Resort \u0026amp; Spa）\u003c/strong\u003e\u003c/span\u003e\u003c/h4\u003e\n\u003cp\u003e\u003ca href=\"https://www.agoda.com/partners/partnersearch.aspx?pcs=10\u0026amp;cid=1888557\u0026amp;hl=ja\u0026amp;hid=2090182\" target=\"_blank\" rel=\"noopener\"\u003e\u003cimg decoding=\"async\" src=\"//pix8.agoda.net/hotelImages/2090182/-1/bec3ba816bdc57b426050ef2033556f8.jpg?ca=9\u0026amp;ce=1\u0026amp;s=480x360\" srcset=\"//pix8.agoda.net/hotelImages/2090182/-1/bec3ba816bdc57b426050ef2033556f8.jpg?ca=9\u0026amp;ce=1\u0026amp;s=480x360 1x, //pix8.agoda.net/hotelImages/2090182/-1/bec3ba816bdc57b426050ef2033556f8.jpg?ca=9\u0026amp;ce=1\u0026amp;s=960x720 2x\" /\u003e\u003c/a\u003e\u003c/p\u003e\n\u003cp\u003e\u003cem\u003e　\u003c/em\u003eこちらのホテルは市内中心部、旧市街の西側に位置しています。黄色と木を基調とした可愛らしいホテルでアジアの雰囲気を感じるリゾートです。こちらのホテルも2022年度のAgoda トラベラーズ ベストチョイス賞にも選ばれているホテルで、近年注目度が上がっています。旧市街からは少し離れているため、静かでゆったりとした時間を過ごせます。旧市街へは徒歩で15分ほどです。歩き疲れたり、早く行きたい時はホテルから送迎バスが出ているのでうまく活用してホイアンの街を楽しみましょう。また少し足を伸ばしてフエやダナンへ行きたい方はホテルでタクシーの手配をしてくれるので近郊へのアクセスも心配いりません。日本語を話せるスタッフはいませんが、スタッフはとてもフレンドリーで親切なので、ベトナムの旅行が初めてで不安な方でも大丈夫です。朝食はビュッフェスタイルで、ベトナムのローカルフードも食べられます。プールは2つあり、プールサイドでゆっくり過ごすのも良いでしょう。ホイアンで静かにゆったりと過ごしたい方、観光を楽しみたい方はぜひチェックしてみてください。\u003c/p\u003e\n\u003cdiv class=\"al-c m20\"\u003e\u003ca href=\"https://www.agoda.com/partners/partnersearch.aspx?pcs=1\u0026amp;cid=1888557\u0026amp;hl=ja-jp\u0026amp;hid=2090182\" class=\"btn dir-arw_r btn_bluegreen\" target=\"_blank\" rel=\"noopener noreferrer\"\u003e\u003cspan class=\"icon_arrow_s_right\"\u003e\u003c/span\u003eアゴダで「ラ シエスタ ホイ アン リゾート＆スパ」を予約する\u003c/a\u003e\u003c/div\u003e\n\u003cdiv class=\"box_style box_style02\"\u003e\n\u003cdiv class=\"box_inner\"\u003e\n\u003cp\u003e\u003cspan class=\"orange b\"\u003eラ シエスタ ホイ アン リゾート＆スパ（La Siesta Hoi An Resort \u0026amp; Spa）\u003c/span\u003e\u003cbr /\u003e\n住所：132 Hung Vuong, タインハー, ホイアン, ベトナム\u003cbr /\u003e\nURL：\u003ca href=\"https://lasiestaresorts.com/\" target=\"_blank\" rel=\"noopener noreferrer\"\u003ehttps://lasiestaresorts.com/\u003c/a\u003e\u003c/p\u003e\n\u003cp\u003e\u003ciframe width=\"600\" height=\"450\" style=\"border: 0;\" src=\"https://www.google.com/maps/embed?pb=!1m18!1m12!1m3!1d3837.5540851081073!2d108.31419951487254!3d15.880016948698895!2m3!1f0!2f0!3f0!3m2!1i1024!2i768!4f13.1!3m3!1m2!1s0x31420f20fc490bfd%3A0xf39639f84338716c!2sLa%20Siesta%20Hoi%20An%20Resort%20%26%20Spa!5e0!3m2!1sja!2sjp!4v1672035805702!5m2!1sja!2sjp\" allowfullscreen=\"allowfullscreen\" loading=\"lazy\" referrerpolicy=\"no-referrer-when-downgrade\"\u003e\u003c/iframe\u003e\u003c/p\u003e\n\u003c/div\u003e\n\u003c/div\u003e\n\u003ch4\u003e\u003cspan class=\"line-yellow\"\u003e\u003cstrong\u003eシルク センス ホイアン リバー リゾート（Silk Sense Hoi An River Resort）\u003c/strong\u003e\u003c/span\u003e\u003c/h4\u003e\n\u003cp\u003e\u003ca href=\"https://www.agoda.com/partners/partnersearch.aspx?pcs=10\u0026amp;cid=1888557\u0026amp;hl=ja\u0026amp;hid=2225333\" target=\"_blank\" rel=\"noopener\"\u003e\u003cimg decoding=\"async\" src=\"//pix8.agoda.net/hotelImages/2225333/-1/97b50f3074fd3b4d5ebb0116a602c9bb.jpg?ca=11\u0026amp;ce=1\u0026amp;s=480x360\" srcset=\"//pix8.agoda.net/hotelImages/2225333/-1/97b50f3074fd3b4d5ebb0116a602c9bb.jpg?ca=11\u0026amp;ce=1\u0026amp;s=480x360 1x, //pix8.agoda.net/hotelImages/2225333/-1/97b50f3074fd3b4d5ebb0116a602c9bb.jpg?ca=11\u0026amp;ce=1\u0026amp;s=960x720 2x\" /\u003e\u003c/a\u003e\u003c/p\u003e\n\u003cp\u003e\u003cem\u003e　\u003c/em\u003eこちらのホテルは今回紹介している6つの高級5つ星ホテルの中で最もリーズナブルです。5つ星ホテルに泊まってみたいけどなかなか手が出ない方にぜひチェックしていただきたいです。こちらのホテルは市街地から北に約4km離れた場所にあります。ビーチと旧市街の間にあるため、どちらも楽しみたい方におすすめです。旧市街へのアクセスはホテルから出ているシャトルバスを利用することができます。また無料の自転車貸し出しがあるので、それを利用してホイアンの街を散策するのもいいですね。こちらのホテルにはガーデンビューとリバービューのお部屋があります。どちらも穏やかな雰囲気を感じながら過ごすことができます。館内のレストランではアジア料理やベトナムのローカルフードを食べることができます。ホイアンの雰囲気を味わいたい、5つ星のリゾートホテルに泊まってみたい方にはぜひ行っていただきたいです。\u003c/p\u003e\n\u003cdiv class=\"al-c m20\"\u003e\u003ca href=\"https://www.agoda.com/partners/partnersearch.aspx?pcs=1\u0026amp;cid=1888557\u0026amp;hl=ja-jp\u0026amp;hid=2225333\" class=\"btn dir-arw_r btn_bluegreen\" target=\"_blank\" rel=\"noopener noreferrer\"\u003e\u003cspan class=\"icon_arrow_s_right\"\u003e\u003c/span\u003eアゴダで「シルク センス ホイアン リバー リゾート」を予約する\u003c/a\u003e\u003c/div\u003e\n\u003cdiv class=\"box_style box_style02\"\u003e\n\u003cdiv class=\"box_inner\"\u003e\n\u003cp\u003e\u003cspan class=\"orange b\"\u003eシルク センス ホイアン リバー リゾート（Silk Sense Hoi An River Resort）\u003c/span\u003e\u003cbr /\u003e\n住所：01 Dong Da Street, Cam An Ward, Hoi An City, Quang Nam Province, Vietnam, カムアン, ホイアン, ベトナム\u003cbr /\u003e\nURL：\u003ca href=\"http://www.silksenseresort.com/\" target=\"_blank\" rel=\"noopener noreferrer\"\u003ehttp://www.silksenseresort.com/\u003c/a\u003e\u003c/p\u003e\n\u003cp\u003e\u003ciframe width=\"600\" height=\"450\" style=\"border: 0;\" src=\"https://www.google.com/maps/embed?pb=!1m18!1m12!1m3!1d3837.180508692997!2d108.3547913148727!3d15.89961144818436!2m3!1f0!2f0!3f0!3m2!1i1024!2i768!4f13.1!3m3!1m2!1s0x31420d94a776f361%3A0x3114b55b7adbf4e9!2z44K344Or44KvIOOCu-ODs-OCuSDjg5vjgqTjgqLjg7Mg44Oq44OQ44O8IOODquOCvuODvOODiA!5e0!3m2!1sja!2sjp!4v1672035897816!5m2!1sja!2sjp\" allowfullscreen=\"allowfullscreen\" loading=\"lazy\" referrerpolicy=\"no-referrer-when-downgrade\"\u003e\u003c/iframe\u003e\u003c/p\u003e\n\u003c/div\u003e\n\u003c/div\u003e\n\u003ch4\u003e\u003cspan class=\"line-yellow\"\u003e\u003cstrong\u003eパームガーデン ビーチリゾート＆スパ（Palm Garden Beach Resort \u0026amp; Spa）\u003c/strong\u003e\u003c/span\u003e\u003c/h4\u003e\n\u003cp\u003e\u003ca href=\"https://www.agoda.com/partners/partnersearch.aspx?pcs=10\u0026amp;cid=1888557\u0026amp;hl=ja\u0026amp;hid=65107\" target=\"_blank\" rel=\"noopener\"\u003e\u003cimg decoding=\"async\" src=\"//pix8.agoda.net/hotelImages/65107/-1/b4af13870e27feba1b71c374496edb4f.jpg?ca=13\u0026amp;ce=1\u0026amp;s=480x360\" srcset=\"//pix8.agoda.net/hotelImages/65107/-1/b4af13870e27feba1b71c374496edb4f.jpg?ca=13\u0026amp;ce=1\u0026amp;s=480x360 1x, //pix8.agoda.net/hotelImages/65107/-1/b4af13870e27feba1b71c374496edb4f.jpg?ca=13\u0026amp;ce=1\u0026amp;s=960x720 2x\" /\u003e\u003c/a\u003e\u003c/p\u003e\n\u003cp\u003e\u003cem\u003e　\u003c/em\u003eこちらのホテルは、旧市街とビーチの間に位置しています。パームガーデンという名前の通り、こちらのホテルの庭にはやしの木がたくさん植えられています。ガーデンビューのお部屋を選ぶとこちらのホテルの魅力を十分に感じることができます。旧市街からは少し距離がありますが、ホテルから定期的にシャトルバスが出ています。旧市街へのアクセスも簡単で、観光も十分にできます。こちらのホテルのお部屋はコテージになっているため、周りを気にせず、快適に過ごすことができます。キッズクラブもあるためお子さんも楽しく過ごすことができます。ファミリーステイをしたい方にもおすすめのホテルです。また館内には2つのレストランが併設されていて、Terrace Cafeではベトナムのローカルフードを楽しめます。旧市街から少し離れた場所でゆったりと滞在したい方におすすめです。\u003c/p\u003e\n\u003cdiv class=\"al-c m20\"\u003e\u003ca href=\"https://www.agoda.com/partners/partnersearch.aspx?pcs=1\u0026amp;cid=1888557\u0026amp;hl=ja-jp\u0026amp;hid=65107\" class=\"btn dir-arw_r btn_bluegreen\" target=\"_blank\" rel=\"noopener noreferrer\"\u003e\u003cspan class=\"icon_arrow_s_right\"\u003e\u003c/span\u003eアゴダで「パームガーデン ビーチリゾート＆スパ」を予約する\u003c/a\u003e\u003c/div\u003e\n\u003cdiv class=\"box_style box_style02\"\u003e\n\u003cdiv class=\"box_inner\"\u003e\u003cspan class=\"orange b\"\u003eパームガーデン ビーチリゾート＆スパ（Palm Garden Beach Resort \u0026amp; Spa）\u003c/span\u003e\u003cbr /\u003e\n住所：Lac Long Quan Road , クアダイ, ホイアン, ベトナム\u003cbr /\u003e\nURL：\u003ca href=\"http://palmgardenresort.com.vn/\" target=\"_blank\" rel=\"noopener noreferrer\"\u003ehttp://palmgardenresort.com.vn/\u003c/a\u003e\u003c/div\u003e\n\u003cdiv class=\"box_inner\"\u003e\n\u003cp\u003e\u003ciframe width=\"600\" height=\"450\" style=\"border: 0;\" src=\"https://www.google.com/maps/embed?pb=!1m18!1m12!1m3!1d3837.1577422515497!2d108.3545393247761!3d15.900804812940946!2m3!1f0!2f0!3f0!3m2!1i1024!2i768!4f13.1!3m3!1m2!1s0x31420d9373446877%3A0x4fb17970e7e8b160!2z44OR44O844OgIOOCrOODvOODh-ODsyDjg6rjgr7jg7zjg4g!5e0!3m2!1sja!2sjp!4v1672036023625!5m2!1sja!2sjp\" allowfullscreen=\"allowfullscreen\" loading=\"lazy\" referrerpolicy=\"no-referrer-when-downgrade\"\u003e\u003c/iframe\u003e\u003c/p\u003e\n\u003c/div\u003e\n\u003c/div\u003e\n\u003cp\u003e\u003cem\u003e　\u003c/em\u003e以上、ホイアンに滞在したことがある筆者がおすすめする5つ星の高級ホテルを6つ紹介させていただきました。ランタンと賑やかな雰囲気を楽しみたい方、ベトナムのローカルフードを楽しみたい方、穏やかな旅にしたいと思われている方もぜひホテル選びの参考にしてみてください。\u003c/p\u003e\n\u003cp\u003e\u003cem\u003e　\u003c/em\u003eベトナム中部のご旅行をご検討されている方は下記も合せてご参考になさってください。\u003c/p\u003e\n\u003cblockquote class=\"wp-embedded-content\" data-secret=\"Nm3Vhl6L7W\"\u003e\n\u003cp\u003e\u003ca href=\"https://kyujin.careerlink.asia/blog/%e3%83%80%e3%83%8a%e3%83%b3%e3%81%8a%e3%81%99%e3%81%99%e3%82%81%e3%81%ae%e9%ab%98%e7%b4%9a5%e3%81%a4%e6%98%9f%e3%83%9b%e3%83%86%e3%83%ab/\"\u003eダナンでおすすめの高級5つ星ホテル7選\u003c/a\u003e\u003c/p\u003e\n\u003c/blockquote\u003e\n\u003cp\u003e\u003ciframe loading=\"lazy\" class=\"wp-embedded-content\" sandbox=\"allow-scripts\" security=\"restricted\" style=\"position: absolute; clip: rect(1px, 1px, 1px, 1px);\" title=\"\u0026#8220;ダナンでおすすめの高級5つ星ホテル7選\u0026#8221; \u0026#8212; 暮らすアジア\" src=\"https://kyujin.careerlink.asia/blog/%e3%83%80%e3%83%8a%e3%83%b3%e3%81%8a%e3%81%99%e3%81%99%e3%82%81%e3%81%ae%e9%ab%98%e7%b4%9a5%e3%81%a4%e6%98%9f%e3%83%9b%e3%83%86%e3%83%ab/embed/#?secret=XBnlHWaeDj#?secret=Nm3Vhl6L7W\" data-secret=\"Nm3Vhl6L7W\" width=\"600\" height=\"338\" frameborder=\"0\" marginwidth=\"0\" marginheight=\"0\" scrolling=\"no\"\u003e\u003c/iframe\u003e\u003c/p\u003e\n\u003cblockquote class=\"wp-embedded-content\" data-secret=\"7Y0fUOYIih\"\u003e\n\u003cp\u003e\u003ca href=\"https://kyujin.careerlink.asia/blog/%e3%83%9b%e3%82%a4%e3%82%a2%e3%83%b3%e3%81%8a%e3%81%99%e3%81%99%e3%82%81%e3%81%ae%e9%ab%98%e7%b4%9a5%e3%81%a4%e6%98%9f%e3%83%9b%e3%83%86%e3%83%ab/\"\u003eホイアンでおすすめの高級5つ星ホテル6選\u003c/a\u003e\u003c/p\u003e\n\u003c/blockquote\u003e\n\u003cp\u003e\u003ciframe loading=\"lazy\" class=\"wp-embedded-content\" sandbox=\"allow-scripts\" security=\"restricted\" style=\"position: absolute; clip: rect(1px, 1px, 1px, 1px);\" title=\"\u0026#8220;ホイアンでおすすめの高級5つ星ホテル6選\u0026#8221; \u0026#8212; 暮らすアジア\" src=\"https://kyujin.careerlink.asia/blog/%e3%83%9b%e3%82%a4%e3%82%a2%e3%83%b3%e3%81%8a%e3%81%99%e3%81%99%e3%82%81%e3%81%ae%e9%ab%98%e7%b4%9a5%e3%81%a4%e6%98%9f%e3%83%9b%e3%83%86%e3%83%ab/embed/#?secret=dLXBHH7jDM#?secret=7Y0fUOYIih\" data-secret=\"7Y0fUOYIih\" width=\"600\" height=\"338\" frameborder=\"0\" marginwidth=\"0\" marginheight=\"0\" scrolling=\"no\"\u003e\u003c/iframe\u003e\u003c/p\u003e\n\u003cdiv style=\"background-color: #f0f8ff; border: 2px solid #1e90ff; border-radius: 10px; padding: 20px; margin: 30px 0;\"\u003e\n\u003ch3 style=\"color: #1e90ff; margin-top: 0;\"\u003eベトナムで働くことに興味はありませんか？\u003c/h3\u003e\n\u003cp\u003eキャリアリンクアジアでは、ベトナム・ホーチミン・ハノイの日系企業の求人を多数掲載しています。ベトナムでの就職・転職をお考えの方は、ぜひご覧ください。\u003c/p\u003e\n\u003cp\u003e\u003cstrong\u003e\u003ca href=\"https://kyujin.careerlink.asia/vietnam/job/list\" style=\"color: #1e90ff;\"\u003e▶ ベトナムの求人一覧を見る\u003c/a\u003e\u003c/strong\u003e\u003c/p\u003e\n\u003cp\u003e\u003cstrong\u003e\u003ca href=\"https://kyujin.careerlink.asia/jobseeker/register\" style=\"color: #1e90ff;\"\u003e▶ 無料会員登録はこちら\u003c/a\u003e\u003c/strong\u003e\u003c/p\u003e\n\u003c/div\u003e\n",
                    "protected":  false
                },
    "excerpt":  {
                    "rendered":  "\u003cp\u003e　ホイアンはベトナムの中部、トゥボン川の河口に位置しています。ベトナムの古都ホイアンは1999年に「ホイアンの古い町並み」として世界遺産に登録されました。リゾート地のダナンからも近いところにあり、また違ったベトナムの一面 [\u0026hellip;]\u003c/p\u003e\n",
                    "protected":  false
                },
    "author":  1,
    "featured_media":  5349,
    "comment_status":  "closed",
    "ping_status":  "open",
    "sticky":  false,
    "template":  "",
    "format":  "standard",
    "meta":  {
                 "footnotes":  ""
             },
    "categories":  [
                       25,
                       410,
                       145,
                       140
                   ],
    "tags":  [
                 147,
                 384,
                 142,
                 144
             ],
    "class_list":  {
                       "0":  "post-5345",
                       "1":  "post",
                       "2":  "type-post",
                       "3":  "status-publish",
                       "4":  "format-standard",
                       "5":  "has-post-thumbnail",
                       "7":  "category-vietnam",
                       "8":  "category-hoi-an",
                       "9":  "category-145",
                       "10":  "category-140",
                       "11":  "tag-147",
                       "12":  "tag-384",
                       "13":  "tag-142",
                       "14":  "tag-144"
                   },
    "yoast_head":  "\u003c!-- This site is optimized with the Yoast SEO plugin v26.7 - https://yoast.com/wordpress/plugins/seo/ --\u003e\n\u003ctitle\u003eホイアンでおすすめの高級5つ星ホテル6選 | 暮らすアジア\u003c/title\u003e\n\u003c!-- 管理者の方へ: ページにメタディスクリプションがないため、表示されません。ページ固有に記入するか、[Yoast SEO - 設定] メニューに移動してテンプレートを設定します。 --\u003e\n\u003cmeta name=\"robots\" content=\"index, follow, max-snippet:-1, max-image-preview:large, max-video-preview:-1\" /\u003e\n\u003clink rel=\"canonical\" href=\"https://kyujin.careerlink.asia/blog/ホイアンおすすめの高級5つ星ホテル/\" /\u003e\n\u003cmeta property=\"og:locale\" content=\"ja_JP\" /\u003e\n\u003cmeta property=\"og:type\" content=\"article\" /\u003e\n\u003cmeta property=\"og:title\" content=\"ホイアンでおすすめの高級5つ星ホテル6選 | 暮らすアジア\" /\u003e\n\u003cmeta property=\"og:description\" content=\"　ホイアンはベトナムの中部、トゥボン川の河口に位置しています。ベトナムの古都ホイアンは1999年に「ホイアンの古い町並み」として世界遺産に登録されました。リゾート地のダナンからも近いところにあり、また違ったベトナムの一面 [\u0026hellip;]\" /\u003e\n\u003cmeta property=\"og:url\" content=\"https://kyujin.careerlink.asia/blog/ホイアンおすすめの高級5つ星ホテル/\" /\u003e\n\u003cmeta property=\"og:site_name\" content=\"暮らすアジア\" /\u003e\n\u003cmeta property=\"article:published_time\" content=\"2022-12-29T01:27:17+00:00\" /\u003e\n\u003cmeta property=\"article:modified_time\" content=\"2026-01-17T13:19:47+00:00\" /\u003e\n\u003cmeta property=\"og:image\" content=\"https://kyujin.careerlink.asia/blog/wp-content/uploads/2022/12/ベトナム・ホイアンでおすすめの高級5つ星ホテル6選.jpg\" /\u003e\n\t\u003cmeta property=\"og:image:width\" content=\"960\" /\u003e\n\t\u003cmeta property=\"og:image:height\" content=\"639\" /\u003e\n\t\u003cmeta property=\"og:image:type\" content=\"image/jpeg\" /\u003e\n\u003cmeta name=\"author\" content=\"キャリアリンク編集部\" /\u003e\n\u003cmeta name=\"twitter:card\" content=\"summary_large_image\" /\u003e\n\u003cmeta name=\"twitter:label1\" content=\"執筆者\" /\u003e\n\t\u003cmeta name=\"twitter:data1\" content=\"キャリアリンク編集部\" /\u003e\n\t\u003cmeta name=\"twitter:label2\" content=\"推定読み取り時間\" /\u003e\n\t\u003cmeta name=\"twitter:data2\" content=\"13分\" /\u003e\n\u003cscript type=\"application/ld+json\" class=\"yoast-schema-graph\"\u003e{\"@context\":\"https://schema.org\",\"@graph\":[{\"@type\":\"Article\",\"@id\":\"https://kyujin.careerlink.asia/blog/%e3%83%9b%e3%82%a4%e3%82%a2%e3%83%b3%e3%81%8a%e3%81%99%e3%81%99%e3%82%81%e3%81%ae%e9%ab%98%e7%b4%9a5%e3%81%a4%e6%98%9f%e3%83%9b%e3%83%86%e3%83%ab/#article\",\"isPartOf\":{\"@id\":\"https://kyujin.careerlink.asia/blog/%e3%83%9b%e3%82%a4%e3%82%a2%e3%83%b3%e3%81%8a%e3%81%99%e3%81%99%e3%82%81%e3%81%ae%e9%ab%98%e7%b4%9a5%e3%81%a4%e6%98%9f%e3%83%9b%e3%83%86%e3%83%ab/\"},\"author\":{\"name\":\"キャリアリンク編集部\",\"@id\":\"https://kyujin.careerlink.asia/blog/#/schema/person/9905febc17609f4b17dd7443b467a385\"},\"headline\":\"ホイアンでおすすめの高級5つ星ホテル6選\",\"datePublished\":\"2022-12-29T01:27:17+00:00\",\"dateModified\":\"2026-01-17T13:19:47+00:00\",\"mainEntityOfPage\":{\"@id\":\"https://kyujin.careerlink.asia/blog/%e3%83%9b%e3%82%a4%e3%82%a2%e3%83%b3%e3%81%8a%e3%81%99%e3%81%99%e3%82%81%e3%81%ae%e9%ab%98%e7%b4%9a5%e3%81%a4%e6%98%9f%e3%83%9b%e3%83%86%e3%83%ab/\"},\"wordCount\":146,\"publisher\":{\"@id\":\"https://kyujin.careerlink.asia/blog/#organization\"},\"image\":{\"@id\":\"https://kyujin.careerlink.asia/blog/%e3%83%9b%e3%82%a4%e3%82%a2%e3%83%b3%e3%81%8a%e3%81%99%e3%81%99%e3%82%81%e3%81%ae%e9%ab%98%e7%b4%9a5%e3%81%a4%e6%98%9f%e3%83%9b%e3%83%86%e3%83%ab/#primaryimage\"},\"thumbnailUrl\":\"https://kyujin.careerlink.asia/blog/wp-content/uploads/2022/12/ベトナム・ホイアンでおすすめの高級5つ星ホテル6選.jpg\",\"keywords\":[\"5つ星ホテル\",\"アナンタラ\",\"ホテル\",\"休日\"],\"articleSection\":[\"ベトナム\",\"ホイアン\",\"ホテル\",\"旅行\"],\"inLanguage\":\"ja\"},{\"@type\":\"WebPage\",\"@id\":\"https://kyujin.careerlink.asia/blog/%e3%83%9b%e3%82%a4%e3%82%a2%e3%83%b3%e3%81%8a%e3%81%99%e3%81%99%e3%82%81%e3%81%ae%e9%ab%98%e7%b4%9a5%e3%81%a4%e6%98%9f%e3%83%9b%e3%83%86%e3%83%ab/\",\"url\":\"https://kyujin.careerlink.asia/blog/%e3%83%9b%e3%82%a4%e3%82%a2%e3%83%b3%e3%81%8a%e3%81%99%e3%81%99%e3%82%81%e3%81%ae%e9%ab%98%e7%b4%9a5%e3%81%a4%e6%98%9f%e3%83%9b%e3%83%86%e3%83%ab/\",\"name\":\"ホイアンでおすすめの高級5つ星ホテル6選 | 暮らすアジア\",\"isPartOf\":{\"@id\":\"https://kyujin.careerlink.asia/blog/#website\"},\"primaryImageOfPage\":{\"@id\":\"https://kyujin.careerlink.asia/blog/%e3%83%9b%e3%82%a4%e3%82%a2%e3%83%b3%e3%81%8a%e3%81%99%e3%81%99%e3%82%81%e3%81%ae%e9%ab%98%e7%b4%9a5%e3%81%a4%e6%98%9f%e3%83%9b%e3%83%86%e3%83%ab/#primaryimage\"},\"image\":{\"@id\":\"https://kyujin.careerlink.asia/blog/%e3%83%9b%e3%82%a4%e3%82%a2%e3%83%b3%e3%81%8a%e3%81%99%e3%81%99%e3%82%81%e3%81%ae%e9%ab%98%e7%b4%9a5%e3%81%a4%e6%98%9f%e3%83%9b%e3%83%86%e3%83%ab/#primaryimage\"},\"thumbnailUrl\":\"https://kyujin.careerlink.asia/blog/wp-content/uploads/2022/12/ベトナム・ホイアンでおすすめの高級5つ星ホテル6選.jpg\",\"datePublished\":\"2022-12-29T01:27:17+00:00\",\"dateModified\":\"2026-01-17T13:19:47+00:00\",\"breadcrumb\":{\"@id\":\"https://kyujin.careerlink.asia/blog/%e3%83%9b%e3%82%a4%e3%82%a2%e3%83%b3%e3%81%8a%e3%81%99%e3%81%99%e3%82%81%e3%81%ae%e9%ab%98%e7%b4%9a5%e3%81%a4%e6%98%9f%e3%83%9b%e3%83%86%e3%83%ab/#breadcrumb\"},\"inLanguage\":\"ja\",\"potentialAction\":[{\"@type\":\"ReadAction\",\"target\":[\"https://kyujin.careerlink.asia/blog/%e3%83%9b%e3%82%a4%e3%82%a2%e3%83%b3%e3%81%8a%e3%81%99%e3%81%99%e3%82%81%e3%81%ae%e9%ab%98%e7%b4%9a5%e3%81%a4%e6%98%9f%e3%83%9b%e3%83%86%e3%83%ab/\"]}]},{\"@type\":\"ImageObject\",\"inLanguage\":\"ja\",\"@id\":\"https://kyujin.careerlink.asia/blog/%e3%83%9b%e3%82%a4%e3%82%a2%e3%83%b3%e3%81%8a%e3%81%99%e3%81%99%e3%82%81%e3%81%ae%e9%ab%98%e7%b4%9a5%e3%81%a4%e6%98%9f%e3%83%9b%e3%83%86%e3%83%ab/#primaryimage\",\"url\":\"https://kyujin.careerlink.asia/blog/wp-content/uploads/2022/12/ベトナム・ホイアンでおすすめの高級5つ星ホテル6選.jpg\",\"contentUrl\":\"https://kyujin.careerlink.asia/blog/wp-content/uploads/2022/12/ベトナム・ホイアンでおすすめの高級5つ星ホテル6選.jpg\",\"width\":960,\"height\":639},{\"@type\":\"BreadcrumbList\",\"@id\":\"https://kyujin.careerlink.asia/blog/%e3%83%9b%e3%82%a4%e3%82%a2%e3%83%b3%e3%81%8a%e3%81%99%e3%81%99%e3%82%81%e3%81%ae%e9%ab%98%e7%b4%9a5%e3%81%a4%e6%98%9f%e3%83%9b%e3%83%86%e3%83%ab/#breadcrumb\",\"itemListElement\":[{\"@type\":\"ListItem\",\"position\":1,\"name\":\"ホーム\",\"item\":\"https://kyujin.careerlink.asia/blog/\"},{\"@type\":\"ListItem\",\"position\":2,\"name\":\"ホイアンでおすすめの高級5つ星ホテル6選\"}]},{\"@type\":\"WebSite\",\"@id\":\"https://kyujin.careerlink.asia/blog/#website\",\"url\":\"https://kyujin.careerlink.asia/blog/\",\"name\":\"暮らすアジア\",\"description\":\"東南アジアの”今”を知る人材会社社員と現地在住者が伝える、知ればちょっとアジアがちかくなる情報ブログ\",\"publisher\":{\"@id\":\"https://kyujin.careerlink.asia/blog/#organization\"},\"potentialAction\":[{\"@type\":\"SearchAction\",\"target\":{\"@type\":\"EntryPoint\",\"urlTemplate\":\"https://kyujin.careerlink.asia/blog/?s={search_term_string}\"},\"query-input\":{\"@type\":\"PropertyValueSpecification\",\"valueRequired\":true,\"valueName\":\"search_term_string\"}}],\"inLanguage\":\"ja\"},{\"@type\":\"Organization\",\"@id\":\"https://kyujin.careerlink.asia/blog/#organization\",\"name\":\"キャリアリンクアジア\",\"url\":\"https://kyujin.careerlink.asia/blog/\",\"logo\":{\"@type\":\"ImageObject\",\"inLanguage\":\"ja\",\"@id\":\"https://kyujin.careerlink.asia/blog/#/schema/logo/image/\",\"url\":\"https://kyujin.careerlink.asia/blog/wp-content/uploads/2020/10/logo-1200x1200-1.png\",\"contentUrl\":\"https://kyujin.careerlink.asia/blog/wp-content/uploads/2020/10/logo-1200x1200-1.png\",\"width\":1200,\"height\":1200,\"caption\":\"キャリアリンクアジア\"},\"image\":{\"@id\":\"https://kyujin.careerlink.asia/blog/#/schema/logo/image/\"}},{\"@type\":\"Person\",\"@id\":\"https://kyujin.careerlink.asia/blog/#/schema/person/9905febc17609f4b17dd7443b467a385\",\"name\":\"キャリアリンク編集部\",\"image\":{\"@type\":\"ImageObject\",\"inLanguage\":\"ja\",\"@id\":\"https://kyujin.careerlink.asia/blog/#/schema/person/image/\",\"url\":\"https://secure.gravatar.com/avatar/8701f568badfca4d5276fee58a666445be82904ca0123886d429464825b459be?s=96\u0026d=mm\u0026r=g\",\"contentUrl\":\"https://secure.gravatar.com/avatar/8701f568badfca4d5276fee58a666445be82904ca0123886d429464825b459be?s=96\u0026d=mm\u0026r=g\",\"caption\":\"キャリアリンク編集部\"},\"description\":\"キャリアリンク在籍のスタッフによる記事です。東南アジアの”今”を知る人材会社社員が、知ればちょっとアジアがちかくなる情報を発信していきます！\",\"url\":\"https://kyujin.careerlink.asia/blog/author/careerlinkasia/\"}]}\u003c/script\u003e\n\u003c!-- / Yoast SEO plugin. --\u003e",
    "yoast_head_json":  {
                            "title":  "ホイアンでおすすめの高級5つ星ホテル6選 | 暮らすアジア",
                            "robots":  {
                                           "index":  "index",
                                           "follow":  "follow",
                                           "max-snippet":  "max-snippet:-1",
                                           "max-image-preview":  "max-image-preview:large",
                                           "max-video-preview":  "max-video-preview:-1"
                                       },
                            "canonical":  "https://kyujin.careerlink.asia/blog/ホイアンおすすめの高級5つ星ホテル/",
                            "og_locale":  "ja_JP",
                            "og_type":  "article",
                            "og_title":  "ホイアンでおすすめの高級5つ星ホテル6選 | 暮らすアジア",
                            "og_description":  "　ホイアンはベトナムの中部、トゥボン川の河口に位置しています。ベトナムの古都ホイアンは1999年に「ホイアンの古い町並み」として世界遺産に登録されました。リゾート地のダナンからも近いところにあり、また違ったベトナムの一面 [\u0026hellip;]",
                            "og_url":  "https://kyujin.careerlink.asia/blog/ホイアンおすすめの高級5つ星ホテル/",
                            "og_site_name":  "暮らすアジア",
                            "article_published_time":  "2022-12-29T01:27:17+00:00",
                            "article_modified_time":  "2026-01-17T13:19:47+00:00",
                            "og_image":  [
                                             {
                                                 "width":  960,
                                                 "height":  639,
                                                 "url":  "https://kyujin.careerlink.asia/blog/wp-content/uploads/2022/12/ベトナム・ホイアンでおすすめの高級5つ星ホテル6選.jpg",
                                                 "type":  "image/jpeg"
                                             }
                                         ],
                            "author":  "キャリアリンク編集部",
                            "twitter_card":  "summary_large_image",
                            "twitter_misc":  {
                                                 "執筆者":  "キャリアリンク編集部",
                                                 "推定読み取り時間":  "13分"
                                             },
                            "schema":  {
                                           "@context":  "https://schema.org",
                                           "@graph":  [
                                                          {
                                                              "@type":  "Article",
                                                              "@id":  "https://kyujin.careerlink.asia/blog/%e3%83%9b%e3%82%a4%e3%82%a2%e3%83%b3%e3%81%8a%e3%81%99%e3%81%99%e3%82%81%e3%81%ae%e9%ab%98%e7%b4%9a5%e3%81%a4%e6%98%9f%e3%83%9b%e3%83%86%e3%83%ab/#article",
                                                              "isPartOf":  {
                                                                               "@id":  "https://kyujin.careerlink.asia/blog/%e3%83%9b%e3%82%a4%e3%82%a2%e3%83%b3%e3%81%8a%e3%81%99%e3%81%99%e3%82%81%e3%81%ae%e9%ab%98%e7%b4%9a5%e3%81%a4%e6%98%9f%e3%83%9b%e3%83%86%e3%83%ab/"
                                                                           },
                                                              "author":  {
                                                                             "name":  "キャリアリンク編集部",
                                                                             "@id":  "https://kyujin.careerlink.asia/blog/#/schema/person/9905febc17609f4b17dd7443b467a385"
                                                                         },
                                                              "headline":  "ホイアンでおすすめの高級5つ星ホテル6選",
                                                              "datePublished":  "2022-12-29T01:27:17+00:00",
                                                              "dateModified":  "2026-01-17T13:19:47+00:00",
                                                              "mainEntityOfPage":  {
                                                                                       "@id":  "https://kyujin.careerlink.asia/blog/%e3%83%9b%e3%82%a4%e3%82%a2%e3%83%b3%e3%81%8a%e3%81%99%e3%81%99%e3%82%81%e3%81%ae%e9%ab%98%e7%b4%9a5%e3%81%a4%e6%98%9f%e3%83%9b%e3%83%86%e3%83%ab/"
                                                                                   },
                                                              "wordCount":  146,
                                                              "publisher":  {
                                                                                "@id":  "https://kyujin.careerlink.asia/blog/#organization"
                                                                            },
                                                              "image":  {
                                                                            "@id":  "https://kyujin.careerlink.asia/blog/%e3%83%9b%e3%82%a4%e3%82%a2%e3%83%b3%e3%81%8a%e3%81%99%e3%81%99%e3%82%81%e3%81%ae%e9%ab%98%e7%b4%9a5%e3%81%a4%e6%98%9f%e3%83%9b%e3%83%86%e3%83%ab/#primaryimage"
                                                                        },
                                                              "thumbnailUrl":  "https://kyujin.careerlink.asia/blog/wp-content/uploads/2022/12/ベトナム・ホイアンでおすすめの高級5つ星ホテル6選.jpg",
                                                              "keywords":  [
                                                                               "5つ星ホテル",
                                                                               "アナンタラ",
                                                                               "ホテル",
                                                                               "休日"
                                                                           ],
                                                              "articleSection":  [
                                                                                     "ベトナム",
                                                                                     "ホイアン",
                                                                                     "ホテル",
                                                                                     "旅行"
                                                                                 ],
                                                              "inLanguage":  "ja"
                                                          },
                                                          {
                                                              "@type":  "WebPage",
                                                              "@id":  "https://kyujin.careerlink.asia/blog/%e3%83%9b%e3%82%a4%e3%82%a2%e3%83%b3%e3%81%8a%e3%81%99%e3%81%99%e3%82%81%e3%81%ae%e9%ab%98%e7%b4%9a5%e3%81%a4%e6%98%9f%e3%83%9b%e3%83%86%e3%83%ab/",
                                                              "url":  "https://kyujin.careerlink.asia/blog/%e3%83%9b%e3%82%a4%e3%82%a2%e3%83%b3%e3%81%8a%e3%81%99%e3%81%99%e3%82%81%e3%81%ae%e9%ab%98%e7%b4%9a5%e3%81%a4%e6%98%9f%e3%83%9b%e3%83%86%e3%83%ab/",
                                                              "name":  "ホイアンでおすすめの高級5つ星ホテル6選 | 暮らすアジア",
                                                              "isPartOf":  {
                                                                               "@id":  "https://kyujin.careerlink.asia/blog/#website"
                                                                           },
                                                              "primaryImageOfPage":  {
                                                                                         "@id":  "https://kyujin.careerlink.asia/blog/%e3%83%9b%e3%82%a4%e3%82%a2%e3%83%b3%e3%81%8a%e3%81%99%e3%81%99%e3%82%81%e3%81%ae%e9%ab%98%e7%b4%9a5%e3%81%a4%e6%98%9f%e3%83%9b%e3%83%86%e3%83%ab/#primaryimage"
                                                                                     },
                                                              "image":  {
                                                                            "@id":  "https://kyujin.careerlink.asia/blog/%e3%83%9b%e3%82%a4%e3%82%a2%e3%83%b3%e3%81%8a%e3%81%99%e3%81%99%e3%82%81%e3%81%ae%e9%ab%98%e7%b4%9a5%e3%81%a4%e6%98%9f%e3%83%9b%e3%83%86%e3%83%ab/#primaryimage"
                                                                        },
                                                              "thumbnailUrl":  "https://kyujin.careerlink.asia/blog/wp-content/uploads/2022/12/ベトナム・ホイアンでおすすめの高級5つ星ホテル6選.jpg",
                                                              "datePublished":  "2022-12-29T01:27:17+00:00",
                                                              "dateModified":  "2026-01-17T13:19:47+00:00",
                                                              "breadcrumb":  {
                                                                                 "@id":  "https://kyujin.careerlink.asia/blog/%e3%83%9b%e3%82%a4%e3%82%a2%e3%83%b3%e3%81%8a%e3%81%99%e3%81%99%e3%82%81%e3%81%ae%e9%ab%98%e7%b4%9a5%e3%81%a4%e6%98%9f%e3%83%9b%e3%83%86%e3%83%ab/#breadcrumb"
                                                                             },
                                                              "inLanguage":  "ja",
                                                              "potentialAction":  [
                                                                                      {
                                                                                          "@type":  "ReadAction",
                                                                                          "target":  [
                                                                                                         "https://kyujin.careerlink.asia/blog/%e3%83%9b%e3%82%a4%e3%82%a2%e3%83%b3%e3%81%8a%e3%81%99%e3%81%99%e3%82%81%e3%81%ae%e9%ab%98%e7%b4%9a5%e3%81%a4%e6%98%9f%e3%83%9b%e3%83%86%e3%83%ab/"
                                                                                                     ]
                                                                                      }
                                                                                  ]
                                                          },
                                                          {
                                                              "@type":  "ImageObject",
                                                              "inLanguage":  "ja",
                                                              "@id":  "https://kyujin.careerlink.asia/blog/%e3%83%9b%e3%82%a4%e3%82%a2%e3%83%b3%e3%81%8a%e3%81%99%e3%81%99%e3%82%81%e3%81%ae%e9%ab%98%e7%b4%9a5%e3%81%a4%e6%98%9f%e3%83%9b%e3%83%86%e3%83%ab/#primaryimage",
                                                              "url":  "https://kyujin.careerlink.asia/blog/wp-content/uploads/2022/12/ベトナム・ホイアンでおすすめの高級5つ星ホテル6選.jpg",
                                                              "contentUrl":  "https://kyujin.careerlink.asia/blog/wp-content/uploads/2022/12/ベトナム・ホイアンでおすすめの高級5つ星ホテル6選.jpg",
                                                              "width":  960,
                                                              "height":  639
                                                          },
                                                          {
                                                              "@type":  "BreadcrumbList",
                                                              "@id":  "https://kyujin.careerlink.asia/blog/%e3%83%9b%e3%82%a4%e3%82%a2%e3%83%b3%e3%81%8a%e3%81%99%e3%81%99%e3%82%81%e3%81%ae%e9%ab%98%e7%b4%9a5%e3%81%a4%e6%98%9f%e3%83%9b%e3%83%86%e3%83%ab/#breadcrumb",
                                                              "itemListElement":  [
                                                                                      {
                                                                                          "@type":  "ListItem",
                                                                                          "position":  1,
                                                                                          "name":  "ホーム",
                                                                                          "item":  "https://kyujin.careerlink.asia/blog/"
                                                                                      },
                                                                                      {
                                                                                          "@type":  "ListItem",
                                                                                          "position":  2,
                                                                                          "name":  "ホイアンでおすすめの高級5つ星ホテル6選"
                                                                                      }
                                                                                  ]
                                                          },
                                                          {
                                                              "@type":  "WebSite",
                                                              "@id":  "https://kyujin.careerlink.asia/blog/#website",
                                                              "url":  "https://kyujin.careerlink.asia/blog/",
                                                              "name":  "暮らすアジア",
                                                              "description":  "東南アジアの”今”を知る人材会社社員と現地在住者が伝える、知ればちょっとアジアがちかくなる情報ブログ",
                                                              "publisher":  {
                                                                                "@id":  "https://kyujin.careerlink.asia/blog/#organization"
                                                                            },
                                                              "potentialAction":  [
                                                                                      {
                                                                                          "@type":  "SearchAction",
                                                                                          "target":  {
                                                                                                         "@type":  "EntryPoint",
                                                                                                         "urlTemplate":  "https://kyujin.careerlink.asia/blog/?s={search_term_string}"
                                                                                                     },
                                                                                          "query-input":  {
                                                                                                              "@type":  "PropertyValueSpecification",
                                                                                                              "valueRequired":  true,
                                                                                                              "valueName":  "search_term_string"
                                                                                                          }
                                                                                      }
                                                                                  ],
                                                              "inLanguage":  "ja"
                                                          },
                                                          {
                                                              "@type":  "Organization",
                                                              "@id":  "https://kyujin.careerlink.asia/blog/#organization",
                                                              "name":  "キャリアリンクアジア",
                                                              "url":  "https://kyujin.careerlink.asia/blog/",
                                                              "logo":  {
                                                                           "@type":  "ImageObject",
                                                                           "inLanguage":  "ja",
                                                                           "@id":  "https://kyujin.careerlink.asia/blog/#/schema/logo/image/",
                                                                           "url":  "https://kyujin.careerlink.asia/blog/wp-content/uploads/2020/10/logo-1200x1200-1.png",
                                                                           "contentUrl":  "https://kyujin.careerlink.asia/blog/wp-content/uploads/2020/10/logo-1200x1200-1.png",
                                                                           "width":  1200,
                                                                           "height":  1200,
                                                                           "caption":  "キャリアリンクアジア"
                                                                       },
                                                              "image":  {
                                                                            "@id":  "https://kyujin.careerlink.asia/blog/#/schema/logo/image/"
                                                                        }
                                                          },
                                                          {
                                                              "@type":  "Person",
                                                              "@id":  "https://kyujin.careerlink.asia/blog/#/schema/person/9905febc17609f4b17dd7443b467a385",
                                                              "name":  "キャリアリンク編集部",
                                                              "image":  {
                                                                            "@type":  "ImageObject",
                                                                            "inLanguage":  "ja",
                                                                            "@id":  "https://kyujin.careerlink.asia/blog/#/schema/person/image/",
                                                                            "url":  "https://secure.gravatar.com/avatar/8701f568badfca4d5276fee58a666445be82904ca0123886d429464825b459be?s=96\u0026d=mm\u0026r=g",
                                                                            "contentUrl":  "https://secure.gravatar.com/avatar/8701f568badfca4d5276fee58a666445be82904ca0123886d429464825b459be?s=96\u0026d=mm\u0026r=g",
                                                                            "caption":  "キャリアリンク編集部"
                                                                        },
                                                              "description":  "キャリアリンク在籍のスタッフによる記事です。東南アジアの”今”を知る人材会社社員が、知ればちょっとアジアがちかくなる情報を発信していきます！",
                                                              "url":  "https://kyujin.careerlink.asia/blog/author/careerlinkasia/"
                                                          }
                                                      ]
                                       }
                        },
    "_links":  {
                   "self":  [
                                {
                                    "href":  "https://kyujin.careerlink.asia/blog/wp-json/wp/v2/posts/5345",
                                    "targetHints":  {
                                                        "allow":  [
                                                                      "GET",
                                                                      "POST",
                                                                      "PUT",
                                                                      "PATCH",
                                                                      "DELETE"
                                                                  ]
                                                    }
                                }
                            ],
                   "collection":  [
                                      {
                                          "href":  "https://kyujin.careerlink.asia/blog/wp-json/wp/v2/posts"
                                      }
                                  ],
                   "about":  [
                                 {
                                     "href":  "https://kyujin.careerlink.asia/blog/wp-json/wp/v2/types/post"
                                 }
                             ],
                   "author":  [
                                  {
                                      "embeddable":  true,
                                      "href":  "https://kyujin.careerlink.asia/blog/wp-json/wp/v2/users/1"
                                  }
                              ],
                   "replies":  [
                                   {
                                       "embeddable":  true,
                                       "href":  "https://kyujin.careerlink.asia/blog/wp-json/wp/v2/comments?post=5345"
                                   }
                               ],
                   "version-history":  [
                                           {
                                               "count":  1,
                                               "href":  "https://kyujin.careerlink.asia/blog/wp-json/wp/v2/posts/5345/revisions"
                                           }
                                       ],
                   "predecessor-version":  [
                                               {
                                                   "id":  7871,
                                                   "href":  "https://kyujin.careerlink.asia/blog/wp-json/wp/v2/posts/5345/revisions/7871"
                                               }
                                           ],
                   "wp:featuredmedia":  [
                                            {
                                                "embeddable":  true,
                                                "href":  "https://kyujin.careerlink.asia/blog/wp-json/wp/v2/media/5349"
                                            }
                                        ],
                   "wp:attachment":  [
                                         {
                                             "href":  "https://kyujin.careerlink.asia/blog/wp-json/wp/v2/media?parent=5345"
                                         }
                                     ],
                   "wp:term":  [
                                   {
                                       "taxonomy":  "category",
                                       "embeddable":  true,
                                       "href":  "https://kyujin.careerlink.asia/blog/wp-json/wp/v2/categories?post=5345"
                                   },
                                   {
                                       "taxonomy":  "post_tag",
                                       "embeddable":  true,
                                       "href":  "https://kyujin.careerlink.asia/blog/wp-json/wp/v2/tags?post=5345"
                                   }
                               ],
                   "curies":  [
                                  {
                                      "name":  "wp",
                                      "href":  "https://api.w.org/{rel}",
                                      "templated":  true
                                  }
                              ]
               }
}
