[
  {
    "id": 6992,
    "title": "【2026最新】タイの人材紹介会社一覧",
    "slug": "thailand-recruitment-agencies-2026",
    "country": "TH",
    "articleType": "問い合わせ直前",
    "ctaStrength": "Strong",
    "hasB2BCTA": true,
    "hasJobseekerCTA": false,
    "internalLinks": 4,
    "hasHubLink": true,
    "hasLastReviewed": false,
    "hasSources": false,
    "contentLength": 57753
  },
  {
    "id": 6804,
    "title": "【2026最新】ベトナムの人材紹介会社・求人転職サイト一覧",
    "slug": "vietnam-recruitment-agencies-2026",
    "country": "VN",
    "articleType": "問い合わせ直前",
    "ctaStrength": "Strong",
    "hasB2BCTA": false,
    "hasJobseekerCTA": false,
    "internalLinks": 4,
    "hasHubLink": true,
    "hasLastReviewed": false,
    "hasSources": false,
    "contentLength": 118988
  },
  {
    "id": 8008,
    "title": "【2025-2026年版】タイ労働法ガイド｜人事・採用担当者向け完全解説",
    "slug": "thailand-labor-law-employer-guide-2025",
    "country": "TH",
    "articleType": "信頼構築",
    "ctaStrength": "Standard",
    "hasB2BCTA": true,
    "hasJobseekerCTA": false,
    "internalLinks": 8,
    "hasHubLink": false,
    "hasLastReviewed": false,
    "hasSources": false,
    "contentLength": 82385
  },
  {
    "id": 7998,
    "title": "ベトナム労働法・雇用規制ガイド2026【経営者・人事担当者向け】",
    "slug": "vietnam-labor-law-employer-guide-2026",
    "country": "VN",
    "articleType": "信頼構築",
    "ctaStrength": "Standard",
    "hasB2BCTA": true,
    "hasJobseekerCTA": false,
    "internalLinks": 11,
    "hasHubLink": true,
    "hasLastReviewed": false,
    "hasSources": false,
    "contentLength": 41905
  },
  {
    "id": 8128,
    "title": "タイ解雇規定完全ガイド2026【法定手続き・補償・トラブル対策】",
    "slug": "thailand-dismissal-regulations-guide-2026",
    "country": "TH",
    "articleType": "信頼構築",
    "ctaStrength": "Standard",
    "hasB2BCTA": false,
    "hasJobseekerCTA": true,
    "internalLinks": 3,
    "hasHubLink": true,
    "hasLastReviewed": false,
    "hasSources": false,
    "contentLength": 19115
  },
  {
    "id": 8135,
    "title": "ベトナム解雇規定完全ガイド2026【法定手続き・補償・トラブル対策】",
    "slug": "vietnam-dismissal-regulations-guide-2026",
    "country": "VN",
    "articleType": "信頼構築",
    "ctaStrength": "Standard",
    "hasB2BCTA": false,
    "hasJobseekerCTA": true,
    "internalLinks": 3,
    "hasHubLink": true,
    "hasLastReviewed": false,
    "hasSources": false,
    "contentLength": 26549
  },
  {
    "id": 7997,
    "title": "【2025-2026年版】タイ最低賃金完全ガイド｜改定内容・地域別一覧・日系企業への影響",
    "slug": "thailand-minimum-wage-guide-2025",
    "country": "TH",
    "articleType": "専門性証明",
    "ctaStrength": "Standard",
    "hasB2BCTA": true,
    "hasJobseekerCTA": true,
    "internalLinks": 10,
    "hasHubLink": true,
    "hasLastReviewed": false,
    "hasSources": false,
    "contentLength": 98090
  },
  {
    "id": 7995,
    "title": "【2026年1月施行】ベトナム最低賃金改定ガイド｜地域別金額・日系企業の対応",
    "slug": "vietnam-minimum-wage-2026",
    "country": "VN",
    "articleType": "専門性証明",
    "ctaStrength": "Standard",
    "hasB2BCTA": true,
    "hasJobseekerCTA": true,
    "internalLinks": 4,
    "hasHubLink": true,
    "hasLastReviewed": false,
    "hasSources": false,
    "contentLength": 28596
  },
  {
    "id": 8129,
    "title": "タイ退職金制度完全ガイド2026【法定補償・計算方法・税務】",
    "slug": "thailand-severance-pay-guide-2026",
    "country": "TH",
    "articleType": "信頼構築",
    "ctaStrength": "Standard",
    "hasB2BCTA": false,
    "hasJobseekerCTA": true,
    "internalLinks": 3,
    "hasHubLink": true,
    "hasLastReviewed": false,
    "hasSources": false,
    "contentLength": 16226
  },
  {
    "id": 8136,
    "title": "ベトナム退職金制度完全ガイド2026【法定補償・計算方法・税務】",
    "slug": "vietnam-severance-pay-guide-2026",
    "country": "VN",
    "articleType": "信頼構築",
    "ctaStrength": "Standard",
    "hasB2BCTA": false,
    "hasJobseekerCTA": true,
    "internalLinks": 3,
    "hasHubLink": true,
    "hasLastReviewed": false,
    "hasSources": false,
    "contentLength": 23204
  },
  {
    "id": 8130,
    "title": "タイ社会保険制度完全ガイド2026【加入手続き・給付内容・保険料】",
    "slug": "thailand-social-security-guide-2026",
    "country": "TH",
    "articleType": "信頼構築",
    "ctaStrength": "Standard",
    "hasB2BCTA": false,
    "hasJobseekerCTA": true,
    "internalLinks": 3,
    "hasHubLink": true,
    "hasLastReviewed": false,
    "hasSources": false,
    "contentLength": 19401
  },
  {
    "id": 8137,
    "title": "ベトナム社会保険制度完全ガイド2026【加入手続き・給付内容・保険料】",
    "slug": "vietnam-social-security-guide-2026",
    "country": "VN",
    "articleType": "信頼構築",
    "ctaStrength": "Standard",
    "hasB2BCTA": false,
    "hasJobseekerCTA": true,
    "internalLinks": 3,
    "hasHubLink": true,
    "hasLastReviewed": false,
    "hasSources": false,
    "contentLength": 21981
  },
  {
    "id": 8533,
    "title": "タイ人と働く完全ガイド【2026年版】文化・価値観・マネジメントのコツ",
    "slug": "thailand-working-with-thai-people-guide-2026",
    "country": "TH",
    "articleType": "専門性証明",
    "ctaStrength": "Standard",
    "hasB2BCTA": false,
    "hasJobseekerCTA": true,
    "internalLinks": 5,
    "hasHubLink": true,
    "hasLastReviewed": false,
    "hasSources": false,
    "contentLength": 17882
  },
  {
    "id": 8534,
    "title": "ベトナム人と働く完全ガイド【2026年版】仕事観・コミュニケーション・マネジメント",
    "slug": "vietnam-working-with-vietnamese-people-guide-2026",
    "country": "VN",
    "articleType": "専門性証明",
    "ctaStrength": "Standard",
    "hasB2BCTA": false,
    "hasJobseekerCTA": true,
    "internalLinks": 6,
    "hasHubLink": true,
    "hasLastReviewed": false,
    "hasSources": false,
    "contentLength": 20773
  },
  {
    "id": 8033,
    "title": "タイ日系企業動向・自動車産業完全ガイド2026【EVシフトと求人動向】",
    "slug": "thailand-automotive-industry-2026",
    "country": "TH",
    "articleType": "専門性証明",
    "ctaStrength": "Standard",
    "hasB2BCTA": true,
    "hasJobseekerCTA": false,
    "internalLinks": 4,
    "hasHubLink": true,
    "hasLastReviewed": false,
    "hasSources": false,
    "contentLength": 40073
  },
  {
    "id": 8003,
    "title": "【2026年版】ベトナム日系企業動向｜進出状況・業種別分析・転職市場",
    "slug": "vietnam-japanese-companies-2026",
    "country": "VN",
    "articleType": "専門性証明",
    "ctaStrength": "Standard",
    "hasB2BCTA": true,
    "hasJobseekerCTA": true,
    "internalLinks": 6,
    "hasHubLink": false,
    "hasLastReviewed": false,
    "hasSources": false,
    "contentLength": 43387
  },
  {
    "id": 8117,
    "title": "タイ個人所得税完全ガイド2026【税率・控除・確定申告を徹底解説】",
    "slug": "thailand-personal-income-tax-guide-2026",
    "country": "TH",
    "articleType": "専門性証明",
    "ctaStrength": "Standard",
    "hasB2BCTA": true,
    "hasJobseekerCTA": true,
    "internalLinks": 4,
    "hasHubLink": true,
    "hasLastReviewed": false,
    "hasSources": false,
    "contentLength": 20182
  },
  {
    "id": 8118,
    "title": "ベトナム個人所得税完全ガイド2026【税率・控除・確定申告を徹底解説】",
    "slug": "vietnam-personal-income-tax-guide-2026",
    "country": "VN",
    "articleType": "専門性証明",
    "ctaStrength": "Standard",
    "hasB2BCTA": false,
    "hasJobseekerCTA": true,
    "internalLinks": 4,
    "hasHubLink": true,
    "hasLastReviewed": false,
    "hasSources": false,
    "contentLength": 20670
  },
  {
    "id": 8005,
    "title": "タイ就労ビザ・ワークパーミット完全ガイド【2026年最新】",
    "slug": "thailand-visa-work-permit-guide-2026",
    "country": "TH",
    "articleType": "専門性証明",
    "ctaStrength": "Standard",
    "hasB2BCTA": true,
    "hasJobseekerCTA": true,
    "internalLinks": 11,
    "hasHubLink": true,
    "hasLastReviewed": false,
    "hasSources": false,
    "contentLength": 85200
  },
  {
    "id": 8024,
    "title": "ベトナム外国人雇用規制ガイド2026【転職者向け】労働許可証・ビザ・必要書類を徹底解説",
    "slug": "vietnam-foreign-employment-regulations-2026",
    "country": "VN",
    "articleType": "専門性証明",
    "ctaStrength": "Standard",
    "hasB2BCTA": true,
    "hasJobseekerCTA": true,
    "internalLinks": 6,
    "hasHubLink": true,
    "hasLastReviewed": false,
    "hasSources": false,
    "contentLength": 45316
  }
]